sdeconv/__init__.py
sdeconv/api/__init__.py
sdeconv/api/api.py
sdeconv/api/factory.py
sdeconv/cli/__init__.py
sdeconv/cli/sdeconv.py
sdeconv/cli/spsf.py
sdeconv/core/__init__.py
sdeconv/core/_observers.py
sdeconv/core/_progress_logger.py
sdeconv/core/_settings.py
sdeconv/core/_timing.py
sdeconv/data/__init__.py
sdeconv/data/celegans.tif
sdeconv/data/pollen.tif
sdeconv/data/pollen_poisson_noise_blurred.tif
sdeconv/data/pollen_psf.tif
sdeconv/deconv/__init__.py
sdeconv/deconv/_datasets.py
sdeconv/deconv/_transforms.py
sdeconv/deconv/_unet_2d.py
sdeconv/deconv/_utils.py
sdeconv/deconv/interface.py
sdeconv/deconv/interface_nn.py
sdeconv/deconv/nn_deconv.py
sdeconv/deconv/noise2void.py
sdeconv/deconv/richardson_lucy.py
sdeconv/deconv/self_supervised_nn.py
sdeconv/deconv/spitfire.py
sdeconv/deconv/wiener.py
sdeconv/psfs/__init__.py
sdeconv/psfs/gaussian.py
sdeconv/psfs/gibson_lanni.py
sdeconv/psfs/interface.py
sdeconv/psfs/lorentz.py
tests/__init__.py
tests/deconv/__init__.py
tests/deconv/celegans_richardson_lucy.tif
tests/deconv/celegans_spitfire.tif
tests/deconv/celegans_wiener.tif
tests/deconv/pollen_richardson_lucy.tif
tests/deconv/pollen_spitfire.tif
tests/deconv/pollen_wiener.tif
tests/deconv/test_richardson_lucy.py
tests/deconv/test_spitfire.py
tests/deconv/test_wiener.py
tests/psfs/__init__.py
tests/psfs/gaussian2d.tif
tests/psfs/gaussian3d.tif
tests/psfs/gibsonlanni.tif
tests/psfs/lorentz2d.tif
tests/psfs/lorentz3d.tif
tests/psfs/test_gausian.py
tests/psfs/test_gibsonlanni.py
tests/psfs/test_lorentz.py
sdeconv-1.0.4.dist-info/LICENSE
sdeconv-1.0.4.dist-info/METADATA
sdeconv-1.0.4.dist-info/WHEEL
sdeconv-1.0.4.dist-info/entry_points.txt
sdeconv-1.0.4.dist-info/top_level.txt
sdeconv-1.0.4.dist-info/RECORD
