Metadata-Version: 2.1
Name: sdeconv
Version: 1.0.4
Summary: Implementation of 2D and 3D scientific image deconvolution
Home-page: https://github.com/sylvainprigent/sdeconv
Author: Sylvain Prigent
Author-email: meriadec.prigent@gmail.com
License: BSD 3-Clause
Classifier: Development Status :: 2 - Pre-Alpha
Classifier: Intended Audience :: Developers
Classifier: Topic :: Software Development :: Testing
Classifier: Programming Language :: Python
Classifier: Programming Language :: Python :: 3
Classifier: Programming Language :: Python :: 3.10
Classifier: Programming Language :: Python :: 3.11
Classifier: Operating System :: OS Independent
Classifier: License :: OSI Approved :: BSD License
Requires-Python: >=3.7
License-File: LICENSE
Requires-Dist: scipy>=1.8.1
Requires-Dist: numpy>=1.22.4
Requires-Dist: torch>=1.11.0
Requires-Dist: torchvision>=0.12.0
Requires-Dist: scikit-image>=0.19.2
